granturismo_stats/__init__.py
granturismo_stats/api/__init__.py
granturismo_stats/api/base.py
granturismo_stats/api/event.py
granturismo_stats/api/localization.py
granturismo_stats/api/ranking.py
granturismo_stats/entities/__init__.py
granturismo_stats/entities/event.py
granturismo_stats/entities/profile.py
granturismo_stats/entities/race.py
granturismo_stats/entities/ranking.py
granturismo_stats/entities/rating.py
granturismo_stats/stats/__init__.py
granturismo_stats/stats/qualifying.py
granturismo_stats-0.3.0.dist-info/LICENSE
granturismo_stats-0.3.0.dist-info/METADATA
granturismo_stats-0.3.0.dist-info/WHEEL
granturismo_stats-0.3.0.dist-info/top_level.txt
granturismo_stats-0.3.0.dist-info/RECORD
