Metadata-Version: 2.1
Name: granturismo-stats
Version: 0.3.0
Summary: Retrieve statistics for Gran Turismo Sport
Home-page: https://github.com/DudeNr33/granturismo-stats
Author: Andreas Finkler
Author-email: andi.finkler@gmail.com
License: UNKNOWN
Platform: UNKNOWN
Classifier: Development Status :: 3 - Alpha
Classifier: Programming Language :: Python :: 3
Classifier: License :: OSI Approved :: MIT License
Classifier: Operating System :: OS Independent
Classifier: Topic :: Games/Entertainment :: Simulation
Requires-Python: >=3.5
Requires-Dist: requests
Requires-Dist: numpy
Requires-Dist: dataclasses ; python_version < "3.7"
Provides-Extra: dev
Requires-Dist: tox ; extra == 'dev'
Requires-Dist: setuptools ; extra == 'dev'
Requires-Dist: wheel ; extra == 'dev'
Requires-Dist: twine ; extra == 'dev'
Requires-Dist: check-manifest ; extra == 'dev'
Provides-Extra: tests
Requires-Dist: coverage ; extra == 'tests'
Requires-Dist: pylint ; extra == 'tests'
Requires-Dist: pytest ; extra == 'tests'
Requires-Dist: pytest-cov ; extra == 'tests'
Requires-Dist: pytest-pylint ; extra == 'tests'
Requires-Dist: requests-mock ; extra == 'tests'
